scoper.py
scoper-1.1.0.dist-info/LICENSE
scoper-1.1.0.dist-info/METADATA
scoper-1.1.0.dist-info/WHEEL
scoper-1.1.0.dist-info/top_level.txt
scoper-1.1.0.dist-info/RECORD
