Metadata-Version: 2.1
Name: scoper
Version: 1.1.0
Summary: test a single URL, or a list of URLs, against a Burp Suite-style JSON configuration file to determine in/out-of-scope status
Home-page: https://github.com/bonifield/scoper/
Author: James Bonifield
Author-email: bonifield.tools@gmail.com
License: UNKNOWN
Platform: UNKNOWN
Classifier: Programming Language :: Python :: 3
Classifier: License :: OSI Approved :: MIT License
Classifier: Operating System :: OS Independent
License-File: LICENSE
